easyssp_auth/__init__.py
easyssp_auth/authentication.py
easyssp_auth/py.typed
easyssp_auth_client-1.0.0.dist-info/METADATA
easyssp_auth_client-1.0.0.dist-info/WHEEL
easyssp_auth_client-1.0.0.dist-info/licenses/LICENSE
easyssp_auth_client-1.0.0.dist-info/RECORD
