Metadata-Version: 2.4
Name: easyssp-auth-client
Version: 1.0.0
Summary: A Python client for authenticating with the easySSP Integration APIs.
Project-URL: Homepage, https://www.easy-ssp.com
Project-URL: Release Changelog, https://github.com/exxcellent/easyssp-auth-client-python/releases
Project-URL: Source, https://github.com/exxcellent/easyssp-auth-client-python
Author-email: easySSP Dev Team <easyssp-dev@exxcellent.de>
License: MIT
License-File: LICENSE
Keywords: authentication,client,easySSP,python
Classifier: License :: OSI Approved :: MIT License
Classifier: Operating System :: OS Independent
Classifier: Programming Language :: Python :: 3.11
Requires-Python: >=3.11
Requires-Dist: urllib3>=2.4.0
